[{"data":"2022-03-16","acquired_by_app_immuni":37853,"acquired_by_app_immuni_total":22599325,"acquired_by_web_ts":150661,"acquired_by_web_ts_total":90437933,"acquired_by_web_id":3055,"acquired_by_web_id_total":907019,"acquired_by_web_spid":247240,"acquired_by_web_spid_total":68434839,"acquired_by_operator_ts":23568,"acquired_by_operator_ts_total":17402617,"acquired_by_operator_id":23522,"acquired_by_operator_id_total":5584389,"acquired_by_app_io":554323,"acquired_by_app_io_total":216031011,"acquired_all":1040222,"acquired_all_total":421397133}]