[{"data":"2022-09-09","acquired_by_app_immuni":3926,"acquired_by_app_immuni_total":25733582,"acquired_by_web_ts":14219,"acquired_by_web_ts_total":98065104,"acquired_by_web_id":142,"acquired_by_web_id_total":1042897,"acquired_by_web_spid":18088,"acquired_by_web_spid_total":77457255,"acquired_by_operator_ts":4615,"acquired_by_operator_ts_total":19115601,"acquired_by_operator_id":3269,"acquired_by_operator_id_total":7364911,"acquired_by_app_io":49095,"acquired_by_app_io_total":243063385,"acquired_all":93354,"acquired_all_total":471842735}]