[{"data":"2022-04-22","acquired_by_app_immuni":28590,"acquired_by_app_immuni_total":24521196,"acquired_by_web_ts":81618,"acquired_by_web_ts_total":93908812,"acquired_by_web_id":2157,"acquired_by_web_id_total":979763,"acquired_by_web_spid":85145,"acquired_by_web_spid_total":72838088,"acquired_by_operator_ts":16317,"acquired_by_operator_ts_total":18029400,"acquired_by_operator_id":20941,"acquired_by_operator_id_total":6279920,"acquired_by_app_io":311405,"acquired_by_app_io_total":229687953,"acquired_all":546173,"acquired_all_total":446245132}]