[{"data":"2021-09-26","acquired_by_app_immuni":58793,"acquired_by_app_immuni_total":7653445,"acquired_by_web_ts":167186,"acquired_by_web_ts_total":33667318,"acquired_by_web_id":2283,"acquired_by_web_id_total":210497,"acquired_by_web_spid":43347,"acquired_by_web_spid_total":17278136,"acquired_by_operator_ts":30519,"acquired_by_operator_ts_total":7536999,"acquired_by_operator_id":5326,"acquired_by_operator_id_total":575561,"acquired_by_app_io":588928,"acquired_by_app_io_total":73605088,"acquired_all":896382,"acquired_all_total":140527044}]