[{"data":"2023-10-27","acquired_by_app_immuni":0,"acquired_by_app_immuni_total":26235422,"acquired_by_web_ts":28,"acquired_by_web_ts_total":100338634,"acquired_by_web_id":0,"acquired_by_web_id_total":1051667,"acquired_by_web_spid":113,"acquired_by_web_spid_total":79688050,"acquired_by_operator_ts":130,"acquired_by_operator_ts_total":19999735,"acquired_by_operator_id":3,"acquired_by_operator_id_total":7958622,"acquired_by_app_io":1390,"acquired_by_app_io_total":251317987,"acquired_all":1664,"acquired_all_total":486590117}]