[{"data":"2022-07-05","acquired_by_app_immuni":8525,"acquired_by_app_immuni_total":25183998,"acquired_by_web_ts":30379,"acquired_by_web_ts_total":96119054,"acquired_by_web_id":283,"acquired_by_web_id_total":1028834,"acquired_by_web_spid":26665,"acquired_by_web_spid_total":74980457,"acquired_by_operator_ts":9365,"acquired_by_operator_ts_total":18556510,"acquired_by_operator_id":12895,"acquired_by_operator_id_total":6964507,"acquired_by_app_io":103493,"acquired_by_app_io_total":237133515,"acquired_all":191605,"acquired_all_total":459966875}]