[{"data":"2022-01-26","acquired_by_app_immuni":149568,"acquired_by_app_immuni_total":18638527,"acquired_by_web_ts":585718,"acquired_by_web_ts_total":76382080,"acquired_by_web_id":3222,"acquired_by_web_id_total":755670,"acquired_by_web_spid":373136,"acquired_by_web_spid_total":56476778,"acquired_by_operator_ts":94773,"acquired_by_operator_ts_total":15256345,"acquired_by_operator_id":56611,"acquired_by_operator_id_total":4361737,"acquired_by_app_io":1098474,"acquired_by_app_io_total":180516505,"acquired_all":2361502,"acquired_all_total":352387642}]