[{"data":"2023-06-30","acquired_by_app_immuni":0,"acquired_by_app_immuni_total":26235422,"acquired_by_web_ts":303,"acquired_by_web_ts_total":100333717,"acquired_by_web_id":2,"acquired_by_web_id_total":1051637,"acquired_by_web_spid":600,"acquired_by_web_spid_total":79645625,"acquired_by_operator_ts":288,"acquired_by_operator_ts_total":19980414,"acquired_by_operator_id":119,"acquired_by_operator_id_total":7957849,"acquired_by_app_io":4437,"acquired_by_app_io_total":251007661,"acquired_all":5749,"acquired_all_total":486212325}]